setup.py
tapioca_facebook/__init__.py
tapioca_facebook/resource_mapping.py
tapioca_facebook/tapioca_facebook.py
tapioca_facebook.egg-info/PKG-INFO
tapioca_facebook.egg-info/SOURCES.txt
tapioca_facebook.egg-info/dependency_links.txt
tapioca_facebook.egg-info/not-zip-safe
tapioca_facebook.egg-info/requires.txt
tapioca_facebook.egg-info/top_level.txt