Metadata-Version: 1.1
Name: tapioca-facebook
Version: 0.2.2
Summary: Facebook GraphAPI wrapper using tapioca
Home-page: https://github.com/vintasoftware/tapioca-facebook
Author: Filipe Ximenes
Author-email: filipeximenes@gmail.com
License: BSD
Keywords: tapioca-facebook
Platform: UNKNOWN
Classifier: Development Status :: 2 - Pre-Alpha
Classifier: Intended Audience :: Developers
Classifier: License :: OSI Approved :: BSD License
Classifier: Natural Language :: English
Classifier: Programming Language :: Python :: 2
Classifier: Programming Language :: Python :: 2.7
